ua/__init__.py
ua/enums.py
ua/models.py
ua/parser.py
ua-0.1.5.dist-info/LICENSE
ua-0.1.5.dist-info/WHEEL
ua-0.1.5.dist-info/METADATA
ua-0.1.5.dist-info/RECORD
