Metadata-Version: 2.1
Name: ua
Version: 0.1.5
Summary: User-Agent parsing and creation
Home-page: https://github.com/tombulled/ua
License: MIT
Keywords: python,useragent,ua
Author: Tom Bulled
Author-email: 26026015+tombulled@users.noreply.github.com
Requires-Python: >=3.8,<4.0
Classifier: License :: OSI Approved :: MIT License
Classifier: Programming Language :: Python :: 3
Classifier: Programming Language :: Python :: 3.10
Classifier: Programming Language :: Python :: 3.8
Classifier: Programming Language :: Python :: 3.9
Requires-Dist: parse (>=1.19.0,<2.0.0)
Project-URL: Documentation, https://github.com/tombulled/ua
Project-URL: Repository, https://github.com/tombulled/ua
